Metadata-Version: 2.1
Name: fastapi-cache2
Version: 0.2.0
Summary: Cache for FastAPI
Home-page: https://github.com/long2ice/fastapi-cache
License: Apache-2.0
Keywords: fastapi,cache,caching
Author: long2ice
Author-email: long2ice@gmail.com
Requires-Python: >=3.7,<4.0
Classifier: License :: OSI Approved :: Apache Software License
Classifier: Programming Language :: Python :: 3
Classifier: Programming Language :: Python :: 3.10
Classifier: Programming Language :: Python :: 3.7
Classifier: Programming Language :: Python :: 3.8
Classifier: Programming Language :: Python :: 3.9
Provides-Extra: all
Provides-Extra: dynamodb
Provides-Extra: memcache
Provides-Extra: redis
Requires-Dist: aiobotocore (>=1.4.1,<2.0.0); extra == "dynamodb" or extra == "all"
Requires-Dist: aiohttp (>=3.8.3); python_version >= "3.11"
Requires-Dist: aiomcache; extra == "memcache" or extra == "all"
Requires-Dist: fastapi
Requires-Dist: pendulum
Requires-Dist: redis (>=4.2.0rc1,<5.0.0); extra == "redis" or extra == "all"
Requires-Dist: typing-extensions (>=4.1.0); python_version < "3.10"
Requires-Dist: uvicorn
Project-URL: Documentation, https://github.com/long2ice/fastapi-cache
Project-URL: Repository, https://github.com/long2ice/fastapi-cache.git
